knn_j25ng/__init__.py
knn_j25ng/main.py
knn_j25ng-2.0.3.dist-info/METADATA
knn_j25ng-2.0.3.dist-info/WHEEL
knn_j25ng-2.0.3.dist-info/entry_points.txt
knn_j25ng-2.0.3.dist-info/top_level.txt
knn_j25ng-2.0.3.dist-info/RECORD
