Metadata-Version: 2.1
Name: knn_j25ng
Version: 2.0.3
Summary: Implements KNN model using KNeighborsClassifier
Author-email: j25ng <jsan2861@gmail.com>
License: MIT
Project-URL: Homepage, https://github.com/j25ng/knn_j25ng
Requires-Python: >=3.11
Requires-Dist: numpy >=2.1.1
Requires-Dist: pandas >=2.2.2
Requires-Dist: scikit-learn >=1.5.1
Requires-Dist: matplotlib >=3.9.2
